backpropagation/Backpropagation.py
backpropagation/HyperbolicTangent.py
backpropagation/NeuralNetwork.py
backpropagation/ReLU.py
backpropagation/Sigmoid.py
backpropagation/__init__.py
backpropagation-0.0.3.dist-info/LICENSE.txt
backpropagation-0.0.3.dist-info/METADATA
backpropagation-0.0.3.dist-info/WHEEL
backpropagation-0.0.3.dist-info/top_level.txt
backpropagation-0.0.3.dist-info/RECORD
